pyensure/__init__.py
pyensure/__main__.py
pyensure/state.py
pyensure/test_pyensure.py
pyensure-0.0.3.dist-info/LICENSE
pyensure-0.0.3.dist-info/METADATA
pyensure-0.0.3.dist-info/WHEEL
pyensure-0.0.3.dist-info/top_level.txt
pyensure-0.0.3.dist-info/RECORD
